keygenie/__init__.py
keygenie/cli.py
keygenie/constant.py
keygenie/recoder/__init__.py
keygenie/recoder/recorder.py
keygenie/runner/__init__.py
keygenie/runner/mouse/__init__.py
keygenie/runner/mouse/mouse_operator.py
keygenie/utils/__init__.py
keygenie/utils/decorator.py
keygenie-0.0.1.dist-info/METADATA
keygenie-0.0.1.dist-info/WHEEL
keygenie-0.0.1.dist-info/entry_points.txt
keygenie-0.0.1.dist-info/RECORD
