Metadata-Version: 2.4
Name: keygenie
Version: 0.0.1
Requires-Python: >=3.10
Requires-Dist: pyautogui>=0.9.54
Requires-Dist: pynput>=1.8.0
